modelica_language/__init__.py
modelica_language/util.py
modelica_language/parsers/__init__.py
modelica_language/parsers/regex.py
modelica_language/parsers/syntax/__init__.py
modelica_language/parsers/syntax/_class_definition.py
modelica_language/parsers/syntax/_component_clause.py
modelica_language/parsers/syntax/_equations.py
modelica_language/parsers/syntax/_expressions.py
modelica_language/parsers/syntax/_extends.py
modelica_language/parsers/syntax/_keyword.py
modelica_language/parsers/syntax/_lexical.py
modelica_language/parsers/syntax/_modification.py
modelica_language/parsers/syntax/_stored_definition.py
modelica_language/types/__init__.py
modelica_language/types/abc.py
modelica_language/types/array.py
modelica_language/types/primitive.py
modelicalang/__init__.py
modelicalang/util.py
modelicalang/parsers/__init__.py
modelicalang/parsers/syntax/__init__.py
modelicalang/parsers/syntax/_class_definition.py
modelicalang/parsers/syntax/_component_clause.py
modelicalang/parsers/syntax/_equations.py
modelicalang/parsers/syntax/_expressions.py
modelicalang/parsers/syntax/_extends.py
modelicalang/parsers/syntax/_keyword.py
modelicalang/parsers/syntax/_lexical.py
modelicalang/parsers/syntax/_modification.py
modelicalang/parsers/syntax/_stored_definition.py
modelicalang/types/__init__.py
modelicalang/types/abc.py
modelicalang/types/array.py
modelicalang/types/primitive.py
ModelicaLanguage-0.0.0a6.dist-info/LICENSE
ModelicaLanguage-0.0.0a6.dist-info/METADATA
ModelicaLanguage-0.0.0a6.dist-info/WHEEL
ModelicaLanguage-0.0.0a6.dist-info/top_level.txt
ModelicaLanguage-0.0.0a6.dist-info/RECORD
